README.rst
setup.cfg
setup.py
collective/__init__.py
collective.readunread.egg-info/PKG-INFO
collective.readunread.egg-info/SOURCES.txt
collective.readunread.egg-info/dependency_links.txt
collective.readunread.egg-info/entry_points.txt
collective.readunread.egg-info/namespace_packages.txt
collective.readunread.egg-info/not-zip-safe
collective.readunread.egg-info/paster_plugins.txt
collective.readunread.egg-info/requires.txt
collective.readunread.egg-info/top_level.txt
collective/readunread/README.rst
collective/readunread/__init__.py
collective/readunread/adapters.py
collective/readunread/catalog.py
collective/readunread/configure.zcml
collective/readunread/extender.py
collective/readunread/interfaces.py
collective/readunread/myutils.py
collective/readunread/subscribers.py
collective/readunread/browser/__init__.py
collective/readunread/browser/configure.zcml
collective/readunread/browser/macros.pt
collective/readunread/browser/readunread.css
collective/readunread/browser/readunread.js
collective/readunread/browser/views.py
collective/readunread/locales/collective.readunread.pot
collective/readunread/locales/rebuild.sh
collective/readunread/locales/en/LC_MESSAGES/collective.readunread.po
collective/readunread/locales/it/LC_MESSAGES/collective.readunread.po
collective/readunread/profiles/default/catalog.xml
collective/readunread/profiles/default/cssregistry.xml
collective/readunread/profiles/default/jsregistry.xml
collective/readunread/profiles/default/metadata.xml
collective/readunread/tests/__init__.py
collective/readunread/tests/base.py
collective/readunread/tests/test_doctest.py
collective/readunread/tests/tests.py
docs/CREDITS.txt
docs/HISTORY.html
docs/HISTORY.txt
docs/INSTALL.html
docs/INSTALL.txt
docs/LICENSE.GPL
docs/LICENSE.html
docs/LICENSE.txt