Metadata-Version: 1.0
Name: collective.readunread
Version: 1.0b5
Summary: UNKNOWN
Home-page: https://github.com/collective/collective.readunread
Author: Simone Orsi
Author-email: simahawk@gmail.com
License: GPL
Keywords: Plone
Platform: UNKNOWN
Classifier: Framework :: Plone
Classifier: Programming Language :: Python
